rotowire_client/__init__.py
rotowire_client/default_http_client.py
rotowire_client/manual_tests.py
rotowire_client/roto_wire_client.py
rotowire_client-0.6.dist-info/METADATA
rotowire_client-0.6.dist-info/WHEEL
rotowire_client-0.6.dist-info/top_level.txt
rotowire_client-0.6.dist-info/RECORD
