Metadata-Version: 2.1
Name: rotowire-client
Version: 0.6
Summary: API Consumer for Rotowire
Home-page: https://github.com/ballwiz/rotowire-client
Author: Wedevelop's team
Author-email: rdemasi@gmail.com
License: UNKNOWN
Platform: UNKNOWN
Classifier: License :: OSI Approved :: GNU Lesser General Public License v3 (LGPLv3)
Classifier: Operating System :: POSIX :: Linux
Classifier: Programming Language :: Python :: 3
